{
    "user1": "$2b$12$HCSHVGP.BNOdvEObRpFXL.3IVfmHOIq8cbl/aSMpYrEn.CzppXsw6",
    "user2": "$2b$12$SEtfP6twIcLzuMOjzY9NPOrmlG92.yz5N.c7poc8rTvULxr.fixBm",
    "user3": "$2b$12$MdKoKIt9kWbefPuXAfmkj.tynEPhQikbv2KjxgWfXlfQVZJFU2Okq",
    "user4": "$2b$12$6kIclKq2PV/ZWaEIyYpT0eGExqjIUmp8I3Izl6wQcsRoXFTUZP5Pq",
    "user5": "$2b$12$lLUJM0UDgpoTh5xpP1AIpeKySbIddg0aT2nIj1g4HcfSChtJ/Erjy",
    "user6": "$2b$12$hRtsoou8lb2h7T7fhwF.Re9R7ribOUEaogx15M9LCDH3o4smUne.2",
    "user7": "$2b$12$RdMSKohB7uQgYC2tjKF8uO5vZAXJQFdlIe8xBOx.mJlx9E.pd/d6S"
}